gradio_hls_player/__init__.py
gradio_hls_player/gradio_hls_player.py
gradio_hls_player/gradio_hls_player.pyi
gradio_hls_player/templates/component/Index-Cg-Qn-TX.js
gradio_hls_player/templates/component/_basePickBy-Dd4EmGDl.js
gradio_hls_player/templates/component/_baseUniq-DL0QEthA.js
gradio_hls_player/templates/component/arc-CV7InxbF.js
gradio_hls_player/templates/component/architectureDiagram-IEHRJDOE-CMm9Negu.js
gradio_hls_player/templates/component/blockDiagram-JOT3LUYC-DgoUj14Q.js
gradio_hls_player/templates/component/c4Diagram-VJAJSXHY-B-qtgBo5.js
gradio_hls_player/templates/component/channel-CUaDMpef.js
gradio_hls_player/templates/component/chunk-4BMEZGHF-CiAee28d.js
gradio_hls_player/templates/component/chunk-A2AXSNBT-CcYtVH0s.js
gradio_hls_player/templates/component/chunk-AEK57VVT-epbkH7x0.js
gradio_hls_player/templates/component/chunk-D6G4REZN-DFV40JEy.js
gradio_hls_player/templates/component/chunk-RZ5BOZE2-jsDJJ8WB.js
gradio_hls_player/templates/component/chunk-XZIHB7SX-DX95AzAG.js
gradio_hls_player/templates/component/classDiagram-GIVACNV2-CC3NkWrY.js
gradio_hls_player/templates/component/classDiagram-v2-COTLJTTW-CC3NkWrY.js
gradio_hls_player/templates/component/clone-DLU05apC.js
gradio_hls_player/templates/component/cytoscape.esm-Cl3mOukQ.js
gradio_hls_player/templates/component/dagre-OKDRZEBW-BAmiWH_8.js
gradio_hls_player/templates/component/diagram-SSKATNLV-BCCKyb-C.js
gradio_hls_player/templates/component/diagram-VNBRO52H-Cb8d20cX.js
gradio_hls_player/templates/component/erDiagram-Q7BY3M3F-ClKtMupe.js
gradio_hls_player/templates/component/flowDiagram-4HSFHLVR-D4vMVuMe.js
gradio_hls_player/templates/component/ganttDiagram-APWFNJXF-CjuAJXqR.js
gradio_hls_player/templates/component/gitGraphDiagram-7IBYFJ6S-CPz99gV4.js
gradio_hls_player/templates/component/graph-C7D2pWhQ.js
gradio_hls_player/templates/component/index.js
gradio_hls_player/templates/component/infoDiagram-PH2N3AL5-D9d83k5d.js
gradio_hls_player/templates/component/init-DjUOC4st.js
gradio_hls_player-0.0.1.dist-info/METADATA
gradio_hls_player-0.0.1.dist-info/WHEEL
gradio_hls_player-0.0.1.dist-info/RECORD
